flag_generator.v
module flag_generator #(
    parameter WIDTH = 16
)(
    input  wire [WIDTH-1:0] result,
    input  wire             carry,
    input  wire             overflow,
    output wire             Z,
    output wire             N,
    output wire             C,
    output wire             V
);

    assign Z = (result == 0);
    assign N = result[WIDTH-1];
    assign C = carry;
    assign V = overflow;

endmodule

comparator.v
 module comparator #(
     parameter WIDTH = 16
 )(
     input  wire [WIDTH-1:0] A,
     input  wire [WIDTH-1:0] B,
     input  wire             signed_mode,
     output reg  [2:0]       cmp // [2]=LT, [1]=GT, [0]=EQ
 );

     // Internal wires to hold comparison results
     wire is_eq, is_gt, is_lt;

     // Determine results based on mode using ternary operators
     // This removes the need for duplicated if-else blocks
     assign is_eq = signed_mode ? ($signed(A) == $signed(B)) : (A == B);
     assign is_gt = signed_mode ? ($signed(A) >  $signed(B)) : (A >  B);
     assign is_lt = signed_mode ? ($signed(A) <  $signed(B)) : (A <  B);

     // Combine individual bits into the 3-bit output vector
     // This is much faster to read than 6 different if-else assignments
     always @(*) begin
         cmp = {is_lt, is_gt, is_eq};
     end

 endmodule

divider_restoring.v

module divider_restoring   #(
	parameter WIDTH = 16

)(
    input  wire             clk,
    input  wire             rst,
    input  wire             start,
    input  wire [WIDTH-1:0] A,   // dividend
    input  wire [WIDTH-1:0] B,   // divisor
    output reg  [WIDTH-1:0] quotient,
    output reg  [WIDTH-1:0] remainder,
    output reg              busy,
    output reg              done
);

    reg [WIDTH-1:0] divisor;
    reg [WIDTH:0]   rem;
    reg [$clog2(WIDTH):0] count;

    always @(posedge clk) begin
        if (rst) begin
            quotient  <= 0;
            remainder <= 0;
            divisor   <= 0;
            rem       <= 0;
            count     <= 0;
            busy      <= 0;
            done      <= 0;
        end
        else if (start && !busy) begin
            quotient  <= A;
            divisor   <= B;
            rem       <= 0;
            count     <= WIDTH;
            busy      <= 1;
            done      <= 0;
        end
        else if (busy) begin
            rem <= {rem[WIDTH-1:0], quotient[WIDTH-1]};
            quotient <= quotient << 1;
            rem <= rem - divisor;

            if (rem[WIDTH]) begin
                rem <= rem + divisor;
                quotient[0] <= 0;
            end
            else begin
                quotient[0] <= 1;
            end

            count <= count - 1;

            if (count == 1) begin
                remainder <= rem[WIDTH-1:0];
                busy <= 0;
                done <= 1;
            end
        end
        else begin
            done <= 0;
        end
    end

endmodule

multiplier_shift_add.v
module multiplier_shift_add #(
    parameter WIDTH = 16
)(
    input  wire             clk,
    input  wire             rst,
    input  wire             start,
    input  wire [WIDTH-1:0] A,
    input  wire [WIDTH-1:0] B,
    output reg  [WIDTH-1:0] product,
    output reg              busy,
    output reg              done
);

    reg [WIDTH-1:0] multiplicand;
    reg [WIDTH-1:0] multiplier;
    reg [2*WIDTH-1:0] acc;
    reg [$clog2(WIDTH):0] count;

    always @(posedge clk) begin
        if (rst) begin
            multiplicand <= 0;
            multiplier   <= 0;
            acc          <= 0;
            count        <= 0;
            busy         <= 0;
            done         <= 0;
            product      <= 0;
        end
        else if (start && !busy) begin
            multiplicand <= A;
            multiplier   <= B;
            acc          <= 0;
            count        <= 0;
            busy         <= 1;
            done         <= 0;
        end
        else if (busy) begin
            if (multiplier[0])
                acc <= acc + multiplicand;

            multiplicand <= multiplicand << 1;
            multiplier   <= multiplier >> 1;
            count        <= count + 1;

            if (count == WIDTH-1) begin
                busy    <= 0;
                done    <= 1;
                product <= acc[WIDTH-1:0];
            end
        end
        else begin
            done <= 0;
        end
    end

endmodule

barrel_shifter.v
module barrel_shifter #(
    parameter WIDTH = 16
)(
    input  wire [WIDTH-1:0] data_in,
    input  wire [$clog2(WIDTH)-1:0] shift_amt,
    input  wire [2:0] mode,
    output reg  [WIDTH-1:0] data_out
);

    integer i;
    reg [WIDTH-1:0] temp;

    always @(*) begin
        temp = data_in;

        case (mode)
            // Logical Left Shift
            3'b000: begin
                for (i = 0; i < shift_amt; i = i + 1)
                    temp = {temp[WIDTH-2:0], 1'b0};
            end

            // Logical Right Shift
            3'b001: begin
                for (i = 0; i < shift_amt; i = i + 1)
                    temp = {1'b0, temp[WIDTH-1:1]};
            end

            // Arithmetic Right Shift
            3'b010: begin
                for (i = 0; i < shift_amt; i = i + 1)
                    temp = {temp[WIDTH-1], temp[WIDTH-1:1]};
            end

            // Rotate Left
            3'b011: begin
                for (i = 0; i < shift_amt; i = i + 1)
                    temp = {temp[WIDTH-2:0], temp[WIDTH-1]};
            end

            // Rotate Right
            3'b100: begin
                for (i = 0; i < shift_amt; i = i + 1)
                    temp = {temp[0], temp[WIDTH-1:1]};
            end

            default: temp = data_in;
        endcase

        data_out = temp;
    end

endmodule

logic_unit.v
module logic_unit #(
    parameter WIDTH = 16
)(
    input  wire [WIDTH-1:0] A,
    input  wire [WIDTH-1:0] B,
    input  wire [2:0]       op, // Expanded to 3 bits (0-7)
    output reg [WIDTH-1:0] result
);

    always@(*) begin
        case (op)
            3'b000: result = A & B;        // AND
            3'b001: result = A | B;        // OR
            3'b010: result = A ^ B;        // XOR
            3'b011: result = ~(A ^ B);     // XNOR (Equality check)
            3'b100: result = ~(A & B);     // NAND
            3'b101: result = ~(A | B);     // NOR
            3'b110: result = ~A;           // NOT A (Unary)
            3'b111: result = A;            // PASS A (Transfer)
            default: result = 1'b0;
        endcase
    end

endmodule

adder_subtractor.v
module adder_subtractor #(
    parameter WIDTH = 16
)(
    input  wire [WIDTH-1:0] A,
    input  wire [WIDTH-1:0] B,
    input  wire [1:0]       op,       
    output wire [WIDTH-1:0] result,
    output wire              carry,
    output wire              overflow
);

    wire [WIDTH-1:0] B_int;
    wire             cin;

    
    // Now INC/DEC ignore the external B input entirely
    assign B_int = (op == 2'b01) ? ~B :             // SUB: use 1's complement
                   (op == 2'b10) ? {WIDTH{1'b0}} :  // INC: force B to 0
                   (op == 2'b11) ? {WIDTH{1'b1}} :  // DEC: use -1 (all 1s)
                   B;                               // ADD: use B

    // Carry-in logic: 1 for SUB/INC, 0 for ADD/DEC
    // SUB: A + ~B + 1 = A - B
    // INC: A + 0 + 1  = A + 1
    // DEC: A + (-1) + 0 = A - 1
    assign cin = (op == 2'b01 || op == 2'b10);

    // Optimized Arithmetic using LHS Concatenation
    // Automatically handles the (WIDTH+1) math and extracts carry
    assign {carry, result} = A + B_int + cin;

    // Signed Overflow Detection
    // Logic: Inputs have same sign, but result sign differs
    assign overflow = (A[WIDTH-1] == B_int[WIDTH-1]) && (result[WIDTH-1] != A[WIDTH-1]);

endmodule

alu_top.v
module alu_top #(
    parameter WIDTH = 16
)(
    input  wire              clk,
    input  wire              rst,
    input  wire              start,
    input  wire [3:0]        opcode,
    input  wire [WIDTH-1:0]  A,
    input  wire [WIDTH-1:0]  B,

    output reg  [WIDTH-1:0]  result,
    output wire [WIDTH-1:0]  remainder,
    output wire              busy,
    output wire              done,
    output wire [3:0]        flags
);

    // ------------------------------------------------------------------
    // Internal Wires
    // ------------------------------------------------------------------
    wire [WIDTH-1:0] arith_res, logic_res, shift_res;
    wire [WIDTH-1:0] mul_res, div_res;
    wire [2:0]       comp_res;          // {LT, GT, EQ}
    wire             arith_c, arith_v;
    wire             mul_busy, mul_done;
    wire             div_busy, div_done;

    // ------------------------------------------------------------------
    // Arithmetic Unit
    // ------------------------------------------------------------------
    adder_subtractor #(WIDTH) u_arith (
        .A(A),
        .B(B),
        .op(opcode[1:0]),        // 00 ADD, 01 SUB, 10 INC, 11 DEC
        .result(arith_res),
        .carry(arith_c),
        .overflow(arith_v)
    );

    // ------------------------------------------------------------------
    // Logic Unit
    // ------------------------------------------------------------------
    logic_unit #(WIDTH) u_logic (
        .A(A),
        .B(B),
        .op(opcode[2:0]),
        .result(logic_res)
    );

    // ------------------------------------------------------------------
    // Barrel Shifter
    // ------------------------------------------------------------------
    barrel_shifter #(WIDTH) u_shift (
        .data_in(A),
        .shift_amt(B[$clog2(WIDTH)-1:0]),
        .mode(opcode[2:0]),
        .data_out(shift_res)
    );

    // ------------------------------------------------------------------
    // Multiplier (Sequential)
    // ------------------------------------------------------------------
    multiplier_shift_add #(WIDTH) u_mul (
        .clk(clk),
        .rst(rst),
        .start(start && (opcode == 4'b1000)),
        .A(A),
        .B(B),
        .product(mul_res),
        .busy(mul_busy),
        .done(mul_done)
    );

    // ------------------------------------------------------------------
    // Divider (Sequential)
    // ------------------------------------------------------------------
    divider_restoring #(WIDTH) u_div (
        .clk(clk),
        .rst(rst),
        .start(start && (opcode == 4'b1001)),
        .A(A),
        .B(B),
        .quotient(div_res),
        .remainder(remainder),
        .busy(div_busy),
        .done(div_done)
    );

    // ------------------------------------------------------------------
    // Comparator
    // ------------------------------------------------------------------
    comparator #(WIDTH) u_comp (
        .A(A),
        .B(B),
        .signed_mode(opcode[0]),     // 0 = unsigned, 1 = signed
        .cmp(comp_res)               // {LT, GT, EQ}
    );

    // ------------------------------------------------------------------
    // Output Multiplexer
    // ------------------------------------------------------------------
    always @(*) begin
        result = {WIDTH{1'b0}};
        case (opcode)

            // Arithmetic
            4'b0000, 4'b0001,
            4'b0010, 4'b0011:
                result = arith_res;

            // Logic
            4'b0100, 4'b0101,
            4'b0110, 4'b0111:
                result = logic_res;

            // Multiply (valid only when done)
            4'b1000:
                result = mul_done ? mul_res : {WIDTH{1'b0}};

            // Divide (valid only when done)
            4'b1001:
                result = div_done ? div_res : {WIDTH{1'b0}};

            // Compare
            4'b1010, 4'b1011:
                result = {{WIDTH-3{1'b0}}, comp_res};

            // Shift (LSL, LSR only)
            4'b1100, 4'b1101:
                result = shift_res;

            default:
                result = A;
        endcase
    end

    // ------------------------------------------------------------------
    // Status Signals
    // ------------------------------------------------------------------
wire is_mul = (opcode == 4'b1000);
wire is_div = (opcode == 4'b1001);

assign busy = mul_busy | div_busy;

assign done = is_mul ? mul_done :
              is_div ? div_done :
              1'b1;
 

   // ------------------------------------------------------------------
    // Flags
    // ------------------------------------------------------------------
    wire is_arith = (opcode[3:2] == 2'b00);

    flag_generator #(WIDTH) u_flags (
        .result(result),
        .carry(is_arith ? arith_c : 1'b0),
        .overflow(is_arith ? arith_v : 1'b0),
        .Z(flags[3]),
        .N(flags[2]),
        .C(flags[1]),
        .V(flags[0])
    );

endmodule

alu_tb.v
`timescale 1ns/1ps

module alu_tb;

parameter WIDTH = 16;

reg clk;
reg rst;
reg start;
reg [3:0] opcode;
reg [WIDTH-1:0] A;
reg [WIDTH-1:0] B;

wire [WIDTH-1:0] result;
wire [WIDTH-1:0] remainder;
wire busy;
wire done;
wire [3:0] flags;

// DUT
alu_top #(WIDTH) dut (
    .clk(clk),
    .rst(rst),
    .start(start),
    .opcode(opcode),
    .A(A),
    .B(B),
    .result(result),
    .remainder(remainder),
    .busy(busy),
    .done(done),
    .flags(flags)
);

// Clock generation
always #5 clk = ~clk;

// ---------------------------------------------
// Test Procedure
// ---------------------------------------------
initial begin

    $dumpfile("wave.vcd");
    $dumpvars(0, alu_tb);

    clk = 0;
    rst = 1;
    start = 0;
    #20;
    rst = 0;

    // =============================
    // 1️⃣ ADD
    // =============================
    A = 10; B = 5; opcode = 4'b0000;
    #10;
    $display("ADD Result = %d", result);

    // =============================
    // 2️⃣ SUB
    // =============================
    A = 10; B = 3; opcode = 4'b0001;
    #10;
    $display("SUB Result = %d", result);

    // =============================
    // 3️⃣ LOGIC AND
    // =============================
    A = 8'hF0; B = 8'h0F; opcode = 4'b0100;
    #10;
    $display("LOGIC Result = %h", result);

    // =============================
    // 4️⃣ SHIFT
    // =============================
    A = 16'h0001; B = 2; opcode = 4'b1100;
    #10;
    $display("SHIFT Result = %h", result);

    // =============================
    // 5️⃣ COMPARE
    // =============================
    A = 5; B = 10; opcode = 4'b1010;
    #10;
    $display("COMPARE Result = %b", result);

    // =============================
    // 6️⃣ MULTIPLY
    // =============================
    A = 6; B = 3; opcode = 4'b1000;
    start = 1;
    @(posedge clk);
    start = 0;

    wait(done);
    #10;
    $display("MUL Result = %d", result);

    // =============================
    // 7️⃣ DIVIDE
    // =============================
    A = 13; B = 3; opcode = 4'b1001;
    start = 1;
    @(posedge clk);
    start = 0;

    wait(done);
    #10;
    $display("DIV Result = %d Remainder = %d", result, remainder);

    #50;
    $finish;
end

endmodule

wave.vcd
$date
	Mon Feb 16 16:17:58 2026
$end
$version
	Icarus Verilog
$end
$timescale
	1ps
$end
$scope module alu_tb $end
$var wire 16 ! result [15:0] $end
$var wire 16 " remainder [15:0] $end
$var wire 4 # flags [3:0] $end
$var wire 1 $ done $end
$var wire 1 % busy $end
$var parameter 32 & WIDTH $end
$var reg 16 ' A [15:0] $end
$var reg 16 ( B [15:0] $end
$var reg 1 ) clk $end
$var reg 4 * opcode [3:0] $end
$var reg 1 + rst $end
$var reg 1 , start $end
$scope module dut $end
$var wire 16 - A [15:0] $end
$var wire 16 . B [15:0] $end
$var wire 1 % busy $end
$var wire 1 ) clk $end
$var wire 4 / opcode [3:0] $end
$var wire 1 + rst $end
$var wire 1 , start $end
$var wire 16 0 shift_res [15:0] $end
$var wire 16 1 remainder [15:0] $end
$var wire 16 2 mul_res [15:0] $end
$var wire 1 3 mul_done $end
$var wire 1 4 mul_busy $end
$var wire 16 5 logic_res [15:0] $end
$var wire 1 6 is_mul $end
$var wire 1 7 is_div $end
$var wire 1 8 is_arith $end
$var wire 4 9 flags [3:0] $end
$var wire 1 $ done $end
$var wire 16 : div_res [15:0] $end
$var wire 1 ; div_done $end
$var wire 1 < div_busy $end
$var wire 3 = comp_res [2:0] $end
$var wire 1 > arith_v $end
$var wire 16 ? arith_res [15:0] $end
$var wire 1 @ arith_c $end
$var parameter 32 A WIDTH $end
$var reg 16 B result [15:0] $end
$scope module u_arith $end
$var wire 16 C A [15:0] $end
$var wire 16 D B [15:0] $end
$var wire 1 E cin $end
$var wire 2 F op [1:0] $end
$var wire 1 > overflow $end
$var wire 16 G result [15:0] $end
$var wire 1 @ carry $end
$var wire 16 H B_int [15:0] $end
$var parameter 32 I WIDTH $end
$upscope $end
$scope module u_comp $end
$var wire 16 J A [15:0] $end
$var wire 16 K B [15:0] $end
$var wire 1 L signed_mode $end
$var wire 1 M is_lt $end
$var wire 1 N is_gt $end
$var wire 1 O is_eq $end
$var parameter 32 P WIDTH $end
$var reg 3 Q cmp [2:0] $end
$upscope $end
$scope module u_div $end
$var wire 16 R A [15:0] $end
$var wire 16 S B [15:0] $end
$var wire 1 ) clk $end
$var wire 1 + rst $end
$var wire 1 T start $end
$var parameter 32 U WIDTH $end
$var reg 1 < busy $end
$var reg 5 V count [4:0] $end
$var reg 16 W divisor [15:0] $end
$var reg 1 ; done $end
$var reg 16 X quotient [15:0] $end
$var reg 17 Y rem [16:0] $end
$var reg 16 Z remainder [15:0] $end
$upscope $end
$scope module u_flags $end
$var wire 1 [ C $end
$var wire 1 \ V $end
$var wire 1 ] carry $end
$var wire 1 ^ overflow $end
$var wire 16 _ result [15:0] $end
$var wire 1 ` Z $end
$var wire 1 a N $end
$var parameter 32 b WIDTH $end
$upscope $end
$scope module u_logic $end
$var wire 16 c A [15:0] $end
$var wire 16 d B [15:0] $end
$var wire 3 e op [2:0] $end
$var parameter 32 f WIDTH $end
$var reg 16 g result [15:0] $end
$upscope $end
$scope module u_mul $end
$var wire 16 h A [15:0] $end
$var wire 16 i B [15:0] $end
$var wire 1 ) clk $end
$var wire 1 + rst $end
$var wire 1 j start $end
$var parameter 32 k WIDTH $end
$var reg 32 l acc [31:0] $end
$var reg 1 4 busy $end
$var reg 5 m count [4:0] $end
$var reg 1 3 done $end
$var reg 16 n multiplicand [15:0] $end
$var reg 16 o multiplier [15:0] $end
$var reg 16 p product [15:0] $end
$upscope $end
$scope module u_shift $end
$var wire 16 q data_in [15:0] $end
$var wire 3 r mode [2:0] $end
$var wire 4 s shift_amt [3:0] $end
$var parameter 32 t WIDTH $end
$var reg 16 u data_out [15:0] $end
$var reg 16 v temp [15:0] $end
$var integer 32 w i [31:0] $end
$upscope $end
$upscope $end
$upscope $end
$enddefinitions $end
$comment Show the parameter values. $end
$dumpall
b10000 t
b10000 k
b10000 f
b10000 b
b10000 U
b10000 P
b10000 I
b10000 A
b10000 &
$end
#0
$dumpvars
bx w
bx v
bx u
bx s
bx r
bx q
bx p
bx o
bx n
bx m
bx l
0j
bx i
bx h
bx g
bx e
bx d
bx c
xa
x`
bx _
x^
x]
x\
x[
bx Z
bx Y
bx X
bx W
bx V
0T
bx S
bx R
bx Q
xO
xN
xM
xL
bx K
bx J
bx H
bx G
bx F
xE
bx D
bx C
bx B
x@
bx ?
x>
bx =
x<
x;
bx :
bx 9
x8
x7
x6
bx 5
x4
x3
bx 2
bx 1
bx 0
bx /
bx .
bx -
0,
1+
bx *
0)
bx (
bx '
x%
x$
bx #
bx "
bx !
$end
#5000
0%
bx #
bx 9
x`
bx !
bx B
bx _
b0 2
b0 p
03
04
b0 m
b0 l
b0 o
b0 n
0;
0<
b0 V
b0 Y
b0 W
b0 "
b0 1
b0 Z
b0 :
b0 X
1)
#10000
0)
#15000
1)
#20000
0\
0^
0>
0a
0[
0]
b1111 ?
b1111 G
0@
0E
b101 w
b101 H
b10 =
b10 Q
b0 F
b0 e
b0 r
0L
1$
18
b101 s
0O
1N
0M
b0 5
b0 g
b101000000 0
b101000000 u
b101000000 v
b0 #
b0 9
0`
b1111 !
b1111 B
b1111 _
0)
06
07
b0 *
b0 /
b101 (
b101 .
b101 D
b101 K
b101 S
b101 d
b101 i
b1010 '
b1010 -
b1010 C
b1010 J
b1010 R
b1010 c
b1010 h
b1010 q
0+
#25000
1)
#30000
1[
1]
1@
b111 ?
b111 G
b1111111111111100 H
1E
b1 0
b1 u
b11 w
b1 v
b10 #
b10 9
0`
b111 !
b111 B
b111 _
b1 F
b1 e
b1 r
1L
b11 s
b1011 5
b1011 g
0)
b1 *
b1 /
b11 (
b11 .
b11 D
b11 K
b11 S
b11 d
b11 i
#35000
1)
#40000
1a
0@
0E
0[
0]
b1111 H
b0 F
b100 e
b100 r
0L
08
b1111 s
b11111111 ?
b11111111 G
b1111111111111111 5
b1111111111111111 g
b111100000 0
b111100000 u
b1111 w
b111100000 v
b100 #
b100 9
0`
b1111111111111111 !
b1111111111111111 B
b1111111111111111 _
0)
b100 *
b100 /
b1111 (
b1111 .
b1111 D
b1111 K
b1111 S
b1111 d
b1111 i
b11110000 '
b11110000 -
b11110000 C
b11110000 J
b11110000 R
b11110000 c
b11110000 h
b11110000 q
#45000
1)
#50000
b10 H
b100 =
b100 Q
0a
b10 s
b11 ?
b11 G
0N
1M
b100000000000000 0
b100000000000000 u
b10 w
b100000000000000 v
b0 #
b0 9
0`
b100000000000000 !
b100000000000000 B
b100000000000000 _
0)
b1100 *
b1100 /
b10 (
b10 .
b10 D
b10 K
b10 S
b10 d
b10 i
b1 '
b1 -
b1 C
b1 J
b1 R
b1 c
b1 h
b1 q
#55000
1)
#60000
b0 H
1E
b1111 5
b1111 g
b10 F
b10 e
b10 r
b1010 s
b110 ?
b110 G
b0 0
b0 u
b1010 w
b0 v
b0 #
b0 9
0`
b100 !
b100 B
b100 _
0)
b1010 *
b1010 /
b1010 (
b1010 .
b1010 D
b1010 K
b1010 S
b1010 d
b1010 i
b101 '
b101 -
b101 C
b101 J
b101 R
b101 c
b101 h
b101 q
#65000
1)
#70000
b11 H
0E
b110000 0
b110000 u
b10 =
b10 Q
b0 F
b0 e
b0 r
1j
0$
b11 s
1N
0M
b1001 ?
b1001 G
b10 5
b10 g
b11 w
b110000 v
b1000 #
b1000 9
1`
b0 !
b0 B
b0 _
0)
1,
16
b1000 *
b1000 /
b11 (
b11 .
b11 D
b11 K
b11 S
b11 d
b11 i
b110 '
b110 -
b110 C
b110 J
b110 R
b110 c
b110 h
b110 q
#75000
1%
14
b11 o
b110 n
0j
0,
1)
#80000
0)
#85000
b1 m
b1 o
b1100 n
b110 l
1)
#90000
0)
#95000
b10 m
b0 o
b11000 n
b10010 l
1)
#100000
0)
#105000
b11 m
b110000 n
1)
#110000
0)
#115000
b100 m
b1100000 n
1)
#120000
0)
#125000
b101 m
b11000000 n
1)
#130000
0)
#135000
b110 m
b110000000 n
1)
#140000
0)
#145000
b111 m
b1100000000 n
1)
#150000
0)
#155000
b1000 m
b11000000000 n
1)
#160000
0)
#165000
b1001 m
b110000000000 n
1)
#170000
0)
#175000
b1010 m
b1100000000000 n
1)
#180000
0)
#185000
b1011 m
b11000000000000 n
1)
#190000
0)
#195000
b1100 m
b110000000000000 n
1)
#200000
0)
#205000
b1101 m
b1100000000000000 n
1)
#210000
0)
#215000
b1110 m
b1000000000000000 n
1)
#220000
0)
#225000
b1111 m
b0 n
1)
#230000
0)
#235000
1$
b0 #
b0 9
0`
b10010 !
b10010 B
b10010 _
0%
b10010 2
b10010 p
13
04
b10000 m
1)
#240000
0)
#245000
1%
03
1<
b10000 V
b11 W
b1101 :
b1101 X
1@
b1111111111111100 H
1E
b1 F
b1 e
b1 r
0T
1L
0$
b1010 ?
b1010 G
b1111 5
b1111 g
b1 0
b1 u
b11 w
b1 v
b1000 #
b1000 9
1`
b0 !
b0 B
b0 _
1)
0,
06
17
b1001 *
b1001 /
b1101 '
b1101 -
b1101 C
b1101 J
b1101 R
b1101 c
b1101 h
b1101 q
#250000
0)
#255000
b1111 V
b11111111111111101 Y
b11011 :
b11011 X
1)
#260000
0)
#265000
b1110 V
b110110 :
b110110 X
b0 Y
1)
#270000
0)
#275000
b1101 V
b11111111111111101 Y
b1101101 :
b1101101 X
1)
#280000
0)
#285000
b1100 V
b11011010 :
b11011010 X
b0 Y
1)
#290000
0)
#295000
b1011 V
b11111111111111101 Y
b110110101 :
b110110101 X
1)
#300000
0)
#305000
b1010 V
b1101101010 :
b1101101010 X
b0 Y
1)
#310000
0)
#315000
b1001 V
b11111111111111101 Y
b11011010101 :
b11011010101 X
1)
#320000
0)
#325000
b1000 V
b110110101010 :
b110110101010 X
b0 Y
1)
#330000
0)
#335000
b111 V
b11111111111111101 Y
b1101101010101 :
b1101101010101 X
1)
#340000
0)
#345000
b110 V
b11011010101010 :
b11011010101010 X
b0 Y
1)
#350000
0)
#355000
b101 V
b11111111111111101 Y
b110110101010101 :
b110110101010101 X
1)
#360000
0)
#365000
b100 V
b1101101010101010 :
b1101101010101010 X
b0 Y
1)
#370000
0)
#375000
b11 V
b1011010101010101 :
b1011010101010101 X
b11111111111111101 Y
1)
#380000
0)
#385000
b10 V
b110101010101010 :
b110101010101010 X
b0 Y
1)
#390000
0)
#395000
b1 V
b11111111111111101 Y
b1101010101010101 :
b1101010101010101 X
1)
#400000
0)
#405000
1$
1a
0%
b100 #
b100 9
0`
b1010101010101010 !
b1010101010101010 B
b1010101010101010 _
1;
0<
b1111111111111101 "
b1111111111111101 1
b1111111111111101 Z
b0 V
b1010101010101010 :
b1010101010101010 X
b0 Y
1)
#410000
0)
#415000
0$
0a
b1000 #
b1000 9
1`
b0 !
b0 B
b0 _
0;
1)
